subsystems/__init__.py
subsystems/__main__.py
subsystems/_version.py
subsystems/apps.py
subsystems/config.py
subsystems/main.py
subsystems/main_cli.py
subsystems/servers.py
subsystems/systems.py
subsystems/api/__init__.py
subsystems/api/models.py
subsystems/api/router.py
subsystems/app/asset-manifest.json
subsystems/app/favicon.ico
subsystems/app/index.html
subsystems/app/logo.svg
subsystems/app/manifest.json
subsystems/app/robots.txt
subsystems/app/static/css/main.fc496621.css
subsystems/app/static/css/main.fc496621.css.map
subsystems/app/static/js/787.cda612ba.chunk.js
subsystems/app/static/js/787.cda612ba.chunk.js.map
subsystems/app/static/js/main.f6685f16.js
subsystems/app/static/js/main.f6685f16.js.LICENSE.txt
subsystems/app/static/js/main.f6685f16.js.map
subsystems/app/static/media/react.e6d8e0157b6b1e6f75b1.png
subsystems/extensions/gunicorn.py
subsystems/templates/rocketry.yaml
subsystems/tests/__init__.py
subsystems/tests/conftest.py
subsystems/tests/test_api.py
subsystems/tests/test_apps.py
subsystems/tests/test_cli.py
subsystems/tests/test_config.py
subsystems/tests/test_subsystems.py
subsystems/utils/__init__.py
subsystems/utils/modules.py
subsystems/utils/server.py
subsystems-0.1.0.dist-info/METADATA
subsystems-0.1.0.dist-info/WHEEL
subsystems-0.1.0.dist-info/entry_points.txt
subsystems-0.1.0.dist-info/licenses/LICENCE
subsystems-0.1.0.dist-info/RECORD
