Metadata-Version: 2.1
Name: subsystems
Version: 0.1.0
Summary: Assembler for Pythonic back-end and Javascript front-end
Author-email: Mikael Koli <koli.mikael@gmail.com>
License: MIT License
License-File: LICENCE
Requires-Python: >=3.7
Requires-Dist: fastapi
Requires-Dist: jinja2
Requires-Dist: rocketry
Requires-Dist: sqlalchemy
Requires-Dist: uvicorn[standard]
Provides-Extra: docs
Requires-Dist: pydata-sphinx-theme; extra == 'docs'
Requires-Dist: sphinx-book-theme; extra == 'docs'
Requires-Dist: sphinx-copybutton; extra == 'docs'
Requires-Dist: sphinx-material; extra == 'docs'
Requires-Dist: sphinx>=1.7.5; extra == 'docs'
Provides-Extra: test
Requires-Dist: fastapi; extra == 'test'
Requires-Dist: flask; extra == 'test'
Requires-Dist: gunicorn; extra == 'test'
Requires-Dist: httpx; extra == 'test'
Requires-Dist: pytest; extra == 'test'
Requires-Dist: pytest-asyncio; extra == 'test'
Requires-Dist: requests; extra == 'test'
Requires-Dist: uvicorn[standard]; extra == 'test'
Requires-Dist: waitress; extra == 'test'
